mapper_interactive/__init__.py
mapper_interactive/server.py
mapper_interactive/conf/__init__.py
mapper_interactive/conf/kepler_mapper.py
mapper_interactive-0.0.1.dist-info/LICENSE
mapper_interactive-0.0.1.dist-info/METADATA
mapper_interactive-0.0.1.dist-info/WHEEL
mapper_interactive-0.0.1.dist-info/top_level.txt
mapper_interactive-0.0.1.dist-info/RECORD
